{"text": "[Page 1]\n 1 \nLOI N° 70 -03 PORTANT CODE DE LA FAM ILLE  \n \n \n \nCHAPITRE PRELIMINAIRE  \n \n \nDISPOSITIONS GENERALES  \n \nArticle Premier  \nLa présente loi est dénommée Code de la famille. Elle est désignée dans la suite du présent texte par le \ncode.  \n \nArticle 2  \nLes dispositions du prése nt code s’appliquent:  \n1. à tous les marocains, même ceux portant une autre nationalité;  \n2. aux réfugiés, y compris les apatrides conformément à la convention de Genève du 28 juillet 1951 \nrelative à la situation des réfugiés;  \n3. à toute relation entre deux personnes lorsque l’une des deux parties est marocaine;  \n4. à toute relation entre deux marocains lorsque l’un d’eux est musulman.  \nLes marocains de confession juive sont soumis aux règles du statut personnel hébraïque marocain.  \nPar l’expression « tous les m arocains » mentionnée à l’alinéa 1 et au deuxième paragraphe du présent \narticle, le législateur aura adopté les dispositions du premier paragraphe de l’article 3 du Code de la \nnationalité en date du 6 1 septembre 1958 (*) et abrogé le deuxième alinéa relat if aux  \nexceptions prévues pour les marocains ni musulmans, ni israélites.  \nEn ce qui concerne les apatrides, il y a lieu de signaler que même si le Maroc n’a pas encore ratifié la \nconvention internationale du 28 septembre 1954 qui les intéresse, il n'y a au cun inconvénient à prendre en \nconsidération les principes qui y sont prévus en vue de sauvegarder, le cas échéant, les intérêts de cette \ncatégorie de la population.  \n1 (*) Dahir n° 1 -58-250 (21 safar 1378) portant Code de la nationalité marocaine  \n(B.O. 12 s eptembre 1958) . \n \nArticle 3  \nLe ministère public est partie principale dans toutes les actions visant l’application des dispositions du \nprésent code.  \nL’article 3 a introduit une nouvelle disposition aux termes de laquelle le ministère public est devenu \npartie prenante, c'est -à-dire partie principale dans toutes les actions, alors qu’il n’assumait pas ce rôle et \nn’avait pas cette qualité dans le Code du statut personnel.  \nIl appartient au ministère public de présenter ses conclusions pour chaque dossier, toutes  les fois que sa \nprésence n'a pas été possible, dès lors que le législateur ne sanctionne pas son absence de nullité, dans les \naudiences autres que pénales, conformément aux articles 4 et 7 du Dahir relatif à  \nl’organisation judiciaire.  \n \n \n \n \n \n \n \n ", "metadata": {"page": 1, "doc_id": "Droit.pdf", "source": "C:\\Users\\raara\\AppData\\Local\\Temp\\tmpreksekt3\\Droit.pdf", "type": "pdf"}}